pytest_drf/__init__.py
pytest_drf/authentication.py
pytest_drf/authorization.py
pytest_drf/client.py
pytest_drf/fixtures.py
pytest_drf/pagination.py
pytest_drf/plugin.py
pytest_drf/status.py
pytest_drf/util/__init__.py
pytest_drf/util/expressions.py
pytest_drf/util/metaclasses.py
pytest_drf/util/urls.py
pytest_drf/views.py
pytest_drf-1.1.1.dist-info/entry_points.txt
pytest_drf-1.1.1.dist-info/LICENSE
pytest_drf-1.1.1.dist-info/WHEEL
pytest_drf-1.1.1.dist-info/METADATA
pytest_drf-1.1.1.dist-info/RECORD
